redgettext_babel.py
redgettext_babel-0.1.1.dist-info/METADATA
redgettext_babel-0.1.1.dist-info/WHEEL
redgettext_babel-0.1.1.dist-info/entry_points.txt
redgettext_babel-0.1.1.dist-info/top_level.txt
redgettext_babel-0.1.1.dist-info/RECORD
